companion_configuration_sync/__init__.py
companion_configuration_sync/main.py
krules_companion_sync-0.2.0.dist-info/METADATA
krules_companion_sync-0.2.0.dist-info/WHEEL
krules_companion_sync-0.2.0.dist-info/entry_points.txt
krules_companion_sync-0.2.0.dist-info/RECORD
