Metadata-Version: 2.1
Name: krules-companion-sync
Version: 0.2.0
Summary: KRules Comapnion channels/triggers creation or updates from a yaml file
Author: Kevin Gichia
Author-email: Kevogich@live.com
Requires-Python: >=3.10,<4.0
Classifier: Programming Language :: Python :: 3
Classifier: Programming Language :: Python :: 3.10
Classifier: Programming Language :: Python :: 3.11
Classifier: Programming Language :: Python :: 3.12
Requires-Dist: PyYAML (>=6.0.1,<7.0.0)
Requires-Dist: firebase-admin (>=6.5.0,<7.0.0)
Requires-Dist: typer[all] (>=0.9.0,<0.10.0)
